LICENSE
README.md
setup.py
auto_office.egg-info/PKG-INFO
auto_office.egg-info/SOURCES.txt
auto_office.egg-info/dependency_links.txt
auto_office.egg-info/top_level.txt
autoffice/__init__.py
autoffice/excel/__init__.py
autoffice/excel/adjust.py
autoffice/excel/excel_support.py
autoffice/excel/generate.py
autoffice/excel/style.py
autoffice/file/__init__.py
autoffice/file/base_support.py
autoffice/pdf/__init__.py
autoffice/pdf/pdf_function.py
autoffice/pdf/pdf_support.py
autoffice/word/__init__.py
autoffice/word/word_function.py
autoffice/word/word_support.py