Metadata-Version: 2.1
Name: auto-office
Version: 0.0.3
Summary: auto-office integrates some commonly used office operations to reduce repetitive work
Home-page: 
Author: GYH
Author-email: gyh88077515@163.com
Classifier: Programming Language :: Python :: 3
Classifier: License :: OSI Approved :: MIT License
Classifier: Operating System :: OS Independent
License-File: LICENSE
